choc/ddp/chocolate.py
choc/ddp/translate.py
choc_ddp-0.1.2.dist-info/WHEEL
choc_ddp-0.1.2.dist-info/METADATA
choc_ddp-0.1.2.dist-info/RECORD
